codex_api_client/__init__.py
codex_api_client/api_client.py
codex_api_client/api_response.py
codex_api_client/configuration.py
codex_api_client/exceptions.py
codex_api_client/py.typed
codex_api_client/rest.py
codex_api_client/api/__init__.py
codex_api_client/api/data_api.py
codex_api_client/api/debug_api.py
codex_api_client/api/marketplace_api.py
codex_api_client/api/node_api.py
codex_api_client/models/__init__.py
codex_api_client/models/codex_version.py
codex_api_client/models/content.py
codex_api_client/models/data_item.py
codex_api_client/models/data_list.py
codex_api_client/models/debug_info.py
codex_api_client/models/manifest_item.py
codex_api_client/models/node.py
codex_api_client/models/peer_id_read.py
codex_api_client/models/peers_table.py
codex_api_client/models/purchase.py
codex_api_client/models/reservation.py
codex_api_client/models/sales_availability.py
codex_api_client/models/sales_availability_create.py
codex_api_client/models/sales_availability_read.py
codex_api_client/models/slot.py
codex_api_client/models/slot_agent.py
codex_api_client/models/space.py
codex_api_client/models/spr_read.py
codex_api_client/models/storage_ask.py
codex_api_client/models/storage_request.py
codex_api_client/models/storage_request_creation.py
codex_api_client-0.4.0.dist-info/licenses/LICENSE
codex_api_client-0.4.0.dist-info/METADATA
codex_api_client-0.4.0.dist-info/WHEEL
codex_api_client-0.4.0.dist-info/top_level.txt
codex_api_client-0.4.0.dist-info/RECORD
